{
  "metadata": {
    "stockcode": "C",
    "start_date_param": "01JAN2025",
    "end_date_param": "31DEC2025",
    "rolling_window_days": 63,
    "num_steps": 200,
    "optimization_threshold": 0,
    "h_number_sd": 5,
    "tau_groups_info": [
      {
        "name": "tau_1",
        "range": "0.15-0.35",
        "mean": 0.25
      },
      {
        "name": "tau_2",
        "range": "0.35-0.65",
        "mean": 0.5
      },
      {
        "name": "tau_3",
        "range": "0.75-1.25",
        "mean": 1
      }
    ],
    "option_types_info": [
      "put",
      "call",
      "combined"
    ],
    "time_series_start_date": "2025-11-03",
    "time_series_end_date": "2025-11-13"
  },
  "time_series_data": [
    {
      "date": "2025-11-03T00:00:00",
      "stock_prices": {
        "adjusted": 101.61000061035156
      },
      "bubble_estimates": {
        "daily_grouped": [
          {
            "put": {
              "mu": 0.0,
              "lb": 0.0,
              "ub": 0.0
            },
            "call": {
              "mu": 0.0,
              "lb": 0.0,
              "ub": 0.0
            },
            "combined": {
              "mu": 0.0,
              "lb": 0.0,
              "ub": 0.0
            }
          },
          {
            "put": {
              "mu": 5.565591162685511,
              "lb": -9.512353031423553,
              "ub": 9.643535356794573
            },
            "call": {
              "mu": 2.8798866913597325,
              "lb": 0.5840699931612366,
              "ub": 7.787370056224896
            },
            "combined": {
              "mu": 0.6034364951690577,
              "lb": -1.643020986755957,
              "ub": 4.698227310427407
            }
          },
          {
            "put": {
              "mu": 0.0,
              "lb": 0.0,
              "ub": 0.0
            },
            "call": {
              "mu": 0.0,
              "lb": 0.0,
              "ub": 0.0
            },
            "combined": {
              "mu": 0.0,
              "lb": 0.0,
              "ub": 0.0
            }
          }
        ]
      }
    },
    {
      "date": "2025-11-07T00:00:00",
      "stock_prices": {
        "adjusted": 100.79000091552734
      },
      "bubble_estimates": {
        "daily_grouped": [
          {
            "put": {
              "mu": 2.059755678605054,
              "lb": -0.13901283565911468,
              "ub": 2.2460241928692226
            },
            "call": {
              "mu": 0.4886359244918961,
              "lb": -0.020288857990404224,
              "ub": 0.7500607069741964
            },
            "combined": {
              "mu": 0.4362582220653466,
              "lb": -0.011091256875884498,
              "ub": 0.5886077010065777
            }
          },
          {
            "put": {
              "mu": 7.838412495734118,
              "lb": -5.242132370072528,
              "ub": 10.60812402820743
            },
            "call": {
              "mu": 2.0153609152819083,
              "lb": -0.31615735043572646,
              "ub": 5.6918791809995435
            },
            "combined": {
              "mu": 1.2650835138715,
              "lb": -1.0346610688008755,
              "ub": 4.023994763210543
            }
          },
          {
            "put": {
              "mu": 7.33687128511335,
              "lb": 0.23122765275783522,
              "ub": 7.892514917468866
            },
            "call": {
              "mu": -2.5348883369679953,
              "lb": -3.25258107348918,
              "ub": 1.7753043995531888
            },
            "combined": {
              "mu": 1.0333989268328523,
              "lb": 0.3613303749850972,
              "ub": 1.5604674786806074
            }
          }
        ]
      }
    },
    {
      "date": "2025-11-11T00:00:00",
      "stock_prices": {
        "adjusted": 100.76000213623048
      },
      "bubble_estimates": {
        "daily_grouped": [
          {
            "put": {
              "mu": 1.989511980539883,
              "lb": 0.06379682001574949,
              "ub": 2.21356047439735
            },
            "call": {
              "mu": 0.7196254762822468,
              "lb": 0.21564538561187513,
              "ub": 0.981938900285952
            },
            "combined": {
              "mu": 0.6613056753717936,
              "lb": 0.2122422432385133,
              "ub": 0.8320357741717406
            }
          },
          {
            "put": {
              "mu": 6.848435322464378,
              "lb": -5.512430175993004,
              "ub": 8.957634154255093
            },
            "call": {
              "mu": 1.9816467131395008,
              "lb": -0.42649376367944647,
              "ub": 4.91200941218067
            },
            "combined": {
              "mu": 1.8844125089939958,
              "lb": -0.4958229208291236,
              "ub": 3.9924257165948935
            }
          },
          {
            "put": {
              "mu": 4.8912475234089,
              "lb": 0.1541517685052235,
              "ub": 5.26167661164591
            },
            "call": {
              "mu": -1.6899255579786636,
              "lb": -2.1683873823261197,
              "ub": 1.1835362663687925
            },
            "combined": {
              "mu": 0.6889326178885682,
              "lb": 0.24088691665673145,
              "ub": 1.0403116524537381
            }
          }
        ]
      }
    },
    {
      "date": "2025-11-12T00:00:00",
      "stock_prices": {
        "adjusted": 102.87000274658205
      },
      "bubble_estimates": {
        "daily_grouped": [
          {
            "put": {
              "mu": 2.217138362497321,
              "lb": 0.05791655874861795,
              "ub": 2.4201101662460243
            },
            "call": {
              "mu": 0.969949460977912,
              "lb": 0.500653575018442,
              "ub": 1.2467453469373821
            },
            "combined": {
              "mu": 1.5521085861400115,
              "lb": 1.1546296921381445,
              "ub": 1.7295874801418782
            }
          },
          {
            "put": {
              "mu": 6.686315894825857,
              "lb": -3.9958178393317323,
              "ub": 8.356366295650114
            },
            "call": {
              "mu": 1.3117738961594936,
              "lb": -0.7186383960533053,
              "ub": 3.9917695217056255
            },
            "combined": {
              "mu": 1.71599188671895,
              "lb": -0.2887562210099302,
              "ub": 3.379073327781164
            }
          },
          {
            "put": {
              "mu": 7.641782835414855,
              "lb": 0.10882217882031438,
              "ub": 8.130993492009395
            },
            "call": {
              "mu": -0.5923588635726889,
              "lb": -1.7511567768594862,
              "ub": 2.0814390497141084
            },
            "combined": {
              "mu": 1.3901789407485667,
              "lb": 0.27392238514873063,
              "ub": 1.8701854963484028
            }
          }
        ]
      }
    },
    {
      "date": "2025-11-13T00:00:00",
      "stock_prices": {
        "adjusted": 100.66999816894533
      },
      "bubble_estimates": {
        "daily_grouped": [
          {
            "put": {
              "mu": 2.453212759430089,
              "lb": -0.06817758229012308,
              "ub": 2.6981031011503016
            },
            "call": {
              "mu": 0.815572957614646,
              "lb": 0.3333439847050377,
              "ub": 1.3138019305242543
            },
            "combined": {
              "mu": 1.3218126409310902,
              "lb": 0.9023818368583522,
              "ub": 1.5502434450038278
            }
          },
          {
            "put": {
              "mu": 6.619560908760013,
              "lb": -3.7294818124038156,
              "ub": 8.395936963257176
            },
            "call": {
              "mu": 0.6069005999516304,
              "lb": -1.3404625048550278,
              "ub": 3.6464303714249544
            },
            "combined": {
              "mu": 1.2486473980422195,
              "lb": -0.6698048465868545,
              "ub": 3.0207663093379606
            }
          },
          {
            "put": {
              "mu": 6.113426268331883,
              "lb": 0.0870577430562515,
              "ub": 6.504794793607516
            },
            "call": {
              "mu": -0.47388709085815106,
              "lb": -1.4009254214875888,
              "ub": 1.6651512397712867
            },
            "combined": {
              "mu": 1.1121431525988534,
              "lb": 0.21913790811898454,
              "ub": 1.4961483970787224
            }
          }
        ]
      }
    }
  ]
}